bareasgi_auth_server/__init__.py
bareasgi_auth_server/auth_controller.py
bareasgi_auth_server/auth_service.py
bareasgi_auth_server/types.py
bareasgi_auth_server/utils.py
bareasgi_auth_server-4.0.1.dist-info/WHEEL
bareasgi_auth_server-4.0.1.dist-info/METADATA
bareasgi_auth_server-4.0.1.dist-info/RECORD
